{"blog-static-search-engine":2,"error-typescript-replaceall":2,"my-first-post":3,"nodejs-setup-eslint-shared-config":2,"nodejs-typescript-file-existence-check":2,"pointcloud-websocket-communication":1,"recoil-awesome":7,"web-design-memorandom":2,"zx-hello-world":7,"firebase-switch-prod-stage":1,"gatsby-gsap-erro":1,"gatsby-gsap-error":1,"nestjs-cource1-quickstart":5,"nestjs-cource2-rest-api":7,"nestjs-cource3-rest-api-db":9,"nestjs-cource4-unit-test":2,"nestjs-cource5-graphql":3,"nestjs-graphql-string-cannot-represent-value":1,"nextjs-build-blog":4,"nextjs-typescript-nextpage-invalid-props":4,"npm-how-to-publish-typescript-package":10,"npm-typescript-package-template":1,"pulumi-started-tutorial":9,"react-cra-custom-template-howto":4,"react-d3-line-chart":1,"react-props-default-function":2,"react-testing-hooks":1,"react-warning-componentwillmount-react-helmet":3,"shellscript-create-gatsby-post":1}